{
    "nCountries": 5,
    "Countries": [
        {
            "nFollowers": 3,
            "Name": "Country_6549",
            "DemandParam": {
                "Alpha": 300.0,
                "Beta": 0.7
            },
            "TransportationCosts": [
                0.0,
                1.0,
                1.0,
                1.0,
                1.0
            ],
            "LeaderParam": {
                "ImportLimit": -1.0,
                "ExportLimit": -1.0,
                "PriceLimit": 270.00000000000008
            },
            "Followers": {
                "Names": [
                    "C4365",
                    "G4365",
                    "S3273"
                ],
                "Capacities": [
                    170.0,
                    170.0,
                    50.0
                ],
                "LinearCosts": [
                    220.0,
                    250.0,
                    150.0
                ],
                "QuadraticCosts": [
                    0.2,
                    0.1,
                    0.5
                ],
                "EmissionCosts": [
                    500.0,
                    100.0,
                    50.0
                ],
                "TaxCaps": [
                    300.0,
                    200.0,
                    50.0
                ]
            }
        },
        {
            "nFollowers": 2,
            "Name": "Country_5096",
            "DemandParam": {
                "Alpha": 300.0,
                "Beta": 0.6
            },
            "TransportationCosts": [
                1.0,
                0.0,
                1.0,
                1.0,
                1.0
            ],
            "LeaderParam": {
                "ImportLimit": -1.0,
                "ExportLimit": -1.0,
                "PriceLimit": 270.00000000000008
            },
            "Followers": {
                "Names": [
                    "C3392",
                    "G3392"
                ],
                "Capacities": [
                    100.0,
                    50.0
                ],
                "LinearCosts": [
                    150.0,
                    200.0
                ],
                "QuadraticCosts": [
                    0.5,
                    0.3
                ],
                "EmissionCosts": [
                    500.0,
                    200.0
                ],
                "TaxCaps": [
                    500.0,
                    200.0
                ]
            }
        },
        {
            "nFollowers": 1,
            "Name": "Country_819",
            "DemandParam": {
                "Alpha": 325.0,
                "Beta": 0.9
            },
            "TransportationCosts": [
                1.0,
                1.0,
                0.0,
                1.0,
                1.0
            ],
            "LeaderParam": {
                "ImportLimit": -1.0,
                "ExportLimit": -1.0,
                "PriceLimit": 260.0
            },
            "Followers": {
                "Names": [
                    "C531"
                ],
                "Capacities": [
                    170.0
                ],
                "LinearCosts": [
                    150.0
                ],
                "QuadraticCosts": [
                    0.5
                ],
                "EmissionCosts": [
                    500.0
                ],
                "TaxCaps": [
                    500.0
                ]
            }
        },
        {
            "nFollowers": 2,
            "Name": "Country_8405",
            "DemandParam": {
                "Alpha": 325.0,
                "Beta": 0.6
            },
            "TransportationCosts": [
                1.0,
                1.0,
                1.0,
                0.0,
                1.0
            ],
            "LeaderParam": {
                "ImportLimit": -1.0,
                "ExportLimit": -1.0,
                "PriceLimit": 276.25000000000008
            },
            "Followers": {
                "Names": [
                    "C5597",
                    "G5597"
                ],
                "Capacities": [
                    130.0,
                    170.0
                ],
                "LinearCosts": [
                    200.0,
                    220.0
                ],
                "QuadraticCosts": [
                    0.3,
                    0.2
                ],
                "EmissionCosts": [
                    300.0,
                    200.0
                ],
                "TaxCaps": [
                    500.0,
                    200.0
                ]
            }
        },
        {
            "nFollowers": 3,
            "Name": "Country_1360",
            "DemandParam": {
                "Alpha": 300.0,
                "Beta": 0.7
            },
            "TransportationCosts": [
                1.0,
                1.0,
                1.0,
                1.0,
                0.0
            ],
            "LeaderParam": {
                "ImportLimit": -1.0,
                "ExportLimit": -1.0,
                "PriceLimit": 255.00000000000004
            },
            "Followers": {
                "Names": [
                    "C904",
                    "G904",
                    "S676"
                ],
                "Capacities": [
                    50.0,
                    200.0,
                    50.0
                ],
                "LinearCosts": [
                    150.0,
                    200.0,
                    250.0
                ],
                "QuadraticCosts": [
                    0.5,
                    0.3,
                    0.1
                ],
                "EmissionCosts": [
                    300.0,
                    100.0,
                    50.0
                ],
                "TaxCaps": [
                    300.0,
                    200.0,
                    50.0
                ]
            }
        }
    ]
}