{
    "nCountries": 3,
    "Countries": [
        {
            "nFollowers": 1,
            "Name": "Country_220",
            "DemandParam": {
                "Alpha": 275.0,
                "Beta": 0.9
            },
            "TransportationCosts": [
                0.0,
                1.0,
                1.0
            ],
            "LeaderParam": {
                "ImportLimit": -1.0,
                "ExportLimit": -1.0,
                "PriceLimit": 233.75000000000004,
                "TaxRevenue": true,
                "TaxationType": 0
            },
            "Followers": {
                "Names": [
                    "G148"
                ],
                "Capacities": [
                    130.0
                ],
                "LinearCosts": [
                    250.0
                ],
                "QuadraticCosts": [
                    0.1
                ],
                "EmissionCosts": [
                    200.0
                ],
                "TaxCaps": [
                    100.0
                ]
            }
        },
        {
            "nFollowers": 2,
            "Name": "Country_489",
            "DemandParam": {
                "Alpha": 325.0,
                "Beta": 0.7
            },
            "TransportationCosts": [
                1.0,
                0.0,
                1.0
            ],
            "LeaderParam": {
                "ImportLimit": -1.0,
                "ExportLimit": -1.0,
                "PriceLimit": 292.50000000000008,
                "TaxRevenue": true,
                "TaxationType": 2
            },
            "Followers": {
                "Names": [
                    "C321",
                    "G321"
                ],
                "Capacities": [
                    130.0,
                    100.0
                ],
                "LinearCosts": [
                    220.0,
                    250.0
                ],
                "QuadraticCosts": [
                    0.2,
                    0.1
                ],
                "EmissionCosts": [
                    500.0,
                    200.0
                ],
                "TaxCaps": [
                    500.0,
                    200.0
                ]
            }
        },
        {
            "nFollowers": 2,
            "Name": "Country_697",
            "DemandParam": {
                "Alpha": 275.0,
                "Beta": 0.7
            },
            "TransportationCosts": [
                1.0,
                1.0,
                0.0
            ],
            "LeaderParam": {
                "ImportLimit": -1.0,
                "ExportLimit": -1.0,
                "PriceLimit": 220.0,
                "TaxRevenue": false,
                "TaxationType": 0
            },
            "Followers": {
                "Names": [
                    "C457",
                    "G457"
                ],
                "Capacities": [
                    170.0,
                    1000.0
                ],
                "LinearCosts": [
                    200.0,
                    220.0
                ],
                "QuadraticCosts": [
                    0.3,
                    0.2
                ],
                "EmissionCosts": [
                    300.0,
                    100.0
                ],
                "TaxCaps": [
                    300.0,
                    200.0
                ]
            }
        }
    ]
}